<?xml version="1.0" ?>
<annotation>
  <folder>VOC</folder>
  <filename>4e9164aa-532e-4b76-bce4-060b090da357_0_0_jpg.rf.cb11d1dac5c74bc204dc1ea3000a7525.jpg</filename>
  <source>
    <database>roboflow.ai</database>
  </source>
  <size>
    <width>640</width>
    <height>640</height>
    <depth>3</depth>
  </size>
  <segmented>0</segmented>
  <object>
    <name>aircraft</name>
    <bndbox>
      <xmin>435</xmin>
      <ymin>80</ymin>
      <xmax>479</xmax>
      <ymax>134</ymax>
    </bndbox>
    <polygon>
      <x1>476</x1>
      <y1>80</y1>
      <x2>472</x2>
      <y2>82</y2>
      <x3>463</x3>
      <y3>96</y3>
      <x4>461</x4>
      <y4>96</y4>
      <x5>459</x5>
      <y5>93</y5>
      <x6>457</x6>
      <y6>93</y6>
      <x7>454</x7>
      <y7>97</y7>
      <x8>435</x8>
      <y8>99</y8>
      <x9>439</x9>
      <y9>101</y9>
      <x10>452</x10>
      <y10>103</y10>
      <x11>456</x11>
      <y11>107</y11>
      <x12>449</x12>
      <y12>121</y12>
      <x13>439</x13>
      <y13>125</y13>
      <x14>439</x14>
      <y14>126</y14>
      <x15>444</x15>
      <y15>127</y15>
      <x16>452</x16>
      <y16>134</y16>
      <x17>455</x17>
      <y17>133</y17>
      <x18>453</x18>
      <y18>128</y18>
      <x19>453</x19>
      <y19>123</y19>
      <x20>462</x20>
      <y20>111</y20>
      <x21>464</x21>
      <y21>111</y21>
      <x22>478</x22>
      <y22>126</y22>
      <x23>479</x23>
      <y23>125</y23>
      <x24>479</x24>
      <y24>122</y24>
      <x25>471</x25>
      <y25>107</y25>
      <x26>473</x26>
      <y26>102</y26>
      <x27>469</x27>
      <y27>99</y27>
      <x28>469</x28>
      <y28>97</y28>
      <x29>476</x29>
      <y29>85</y29>
    </polygon>
  </object>
  <object>
    <name>aircraft</name>
    <bndbox>
      <xmin>0</xmin>
      <ymin>0</ymin>
      <xmax>636</xmax>
      <ymax>639</ymax>
    </bndbox>
    <polygon>
      <x1>633</x1>
      <y1>72</y1>
      <x2>631</x2>
      <y2>74</y2>
      <x3>630</x3>
      <y3>71</y3>
      <x4>623</x4>
      <y4>70</y4>
      <x5>620</x5>
      <y5>75</y5>
      <x6>619</x6>
      <y6>84</y6>
      <x7>621</x7>
      <y7>88</y7>
      <x8>619</x8>
      <y8>92</y8>
      <x9>620</x9>
      <y9>97</y9>
      <x10>625</x10>
      <y10>100</y10>
      <x11>624</x11>
      <y11>106</y11>
      <x12>620</x12>
      <y12>104</y12>
      <x13>621</x13>
      <y13>100</y13>
      <x14>614</x14>
      <y14>98</y14>
      <x15>616</x15>
      <y15>90</y15>
      <x16>610</x16>
      <y16>95</y16>
      <x17>611</x17>
      <y17>98</y17>
      <x18>607</x18>
      <y18>103</y18>
      <x19>616</x19>
      <y19>112</y19>
      <x20>613</x20>
      <y20>116</y20>
      <x21>609</x21>
      <y21>114</y21>
      <x22>611</x22>
      <y22>110</y22>
      <x23>602</x23>
      <y23>109</y23>
      <x24>599</x24>
      <y24>111</y24>
      <x25>599</x25>
      <y25>120</y25>
      <x26>586</x26>
      <y26>121</y26>
      <x27>580</x27>
      <y27>126</y27>
      <x28>579</x28>
      <y28>130</y28>
      <x29>573</x29>
      <y29>130</y29>
      <x30>563</x30>
      <y30>137</y30>
      <x31>560</x31>
      <y31>136</y31>
      <x32>562</x32>
      <y32>138</y32>
      <x33>555</x33>
      <y33>140</y33>
      <x34>551</x34>
      <y34>145</y34>
      <x35>548</x35>
      <y35>140</y35>
      <x36>558</x36>
      <y36>134</y36>
      <x37>558</x37>
      <y37>129</y37>
      <x38>545</x38>
      <y38>133</y38>
      <x39>544</x39>
      <y39>128</y39>
      <x40>548</x40>
      <y40>129</y40>
      <x41>550</x41>
      <y41>126</y41>
      <x42>548</x42>
      <y42>120</y42>
      <x43>542</x43>
      <y43>126</y43>
      <x44>538</x44>
      <y44>122</y44>
      <x45>541</x45>
      <y45>116</y45>
      <x46>548</x46>
      <y46>117</y46>
      <x47>548</x47>
      <y47>113</y47>
      <x48>552</x48>
      <y48>111</y48>
      <x49>549</x49>
      <y49>109</y49>
      <x50>548</x50>
      <y50>60</y50>
      <x51>546</x51>
      <y51>63</y51>
      <x52>543</x52>
      <y52>59</y52>
      <x53>542</x53>
      <y53>61</y53>
      <x54>547</x54>
      <y54>68</y54>
      <x55>543</x55>
      <y55>71</y55>
      <x56>544</x56>
      <y56>79</y56>
      <x57>547</x57>
      <y57>79</y57>
      <x58>547</x58>
      <y58>82</y58>
      <x59>544</x59>
      <y59>83</y59>
      <x60>544</x60>
      <y60>89</y60>
      <x61>539</x61>
      <y61>89</y61>
      <x62>539</x62>
      <y62>75</y62>
      <x63>537</x63>
      <y63>75</y63>
      <x64>537</x64>
      <y64>79</y64>
      <x65>530</x65>
      <y65>80</y65>
      <x66>529</x66>
      <y66>71</y66>
      <x67>523</x67>
      <y67>71</y67>
      <x68>521</x68>
      <y68>85</y68>
      <x69>519</x69>
      <y69>81</y69>
      <x70>516</x70>
      <y70>83</y70>
      <x71>512</x71>
      <y71>80</y71>
      <x72>509</x72>
      <y72>81</y72>
      <x73>514</x73>
      <y73>85</y73>
      <x74>512</x74>
      <y74>98</y74>
      <x75>506</x75>
      <y75>104</y75>
      <x76>503</x76>
      <y76>99</y76>
      <x77>499</x77>
      <y77>100</y77>
      <x78>499</x78>
      <y78>104</y78>
      <x79>505</x79>
      <y79>106</y79>
      <x80>501</x80>
      <y80>111</y80>
      <x81>501</x81>
      <y81>118</y81>
      <x82>496</x82>
      <y82>121</y82>
      <x83>493</x83>
      <y83>114</y83>
      <x84>493</x84>
      <y84>118</y84>
      <x85>489</x85>
      <y85>118</y85>
      <x86>488</x86>
      <y86>67</y86>
      <x87>490</x87>
      <y87>60</y87>
      <x88>494</x88>
      <y88>59</y88>
      <x89>496</x89>
      <y89>61</y89>
      <x90>499</x90>
      <y90>58</y90>
      <x91>500</x91>
      <y91>43</y91>
      <x92>506</x92>
      <y92>37</y92>
      <x93>508</x93>
      <y93>38</y93>
      <x94>511</x94>
      <y94>27</y94>
      <x95>518</x95>
      <y95>28</y95>
      <x96>517</x96>
      <y96>21</y96>
      <x97>521</x97>
      <y97>15</y97>
      <x98>524</x98>
      <y98>18</y98>
      <x99>529</x99>
      <y99>17</y99>
      <x100>528</x100>
      <y100>12</y100>
      <x101>531</x101>
      <y101>6</y101>
      <x102>515</x102>
      <y102>5</y102>
      <x103>513</x103>
      <y103>3</y103>
      <x104>511</x104>
      <y104>5</y104>
      <x105>504</x105>
      <y105>2</y105>
      <x106>448</x106>
      <y106>1</y106>
      <x107>441</x107>
      <y107>3</y107>
      <x108>378</x108>
      <y108>2</y108>
      <x109>376</x109>
      <y109>0</y109>
      <x110>373</x110>
      <y110>2</y110>
      <x111>367</x111>
      <y111>0</y111>
      <x112>364</x112>
      <y112>2</y112>
      <x113>360</x113>
      <y113>0</y113>
      <x114>350</x114>
      <y114>0</y114>
      <x115>349</x115>
      <y115>2</y115>
      <x116>346</x116>
      <y116>0</y116>
      <x117>344</x117>
      <y117>2</y117>
      <x118>341</x118>
      <y118>0</y118>
      <x119>311</x119>
      <y119>0</y119>
      <x120>309</x120>
      <y120>2</y120>
      <x121>165</x121>
      <y121>0</y121>
      <x122>160</x122>
      <y122>2</y122>
      <x123>117</x123>
      <y123>3</y123>
      <x124>88</x124>
      <y124>1</y124>
      <x125>79</x125>
      <y125>4</y125>
      <x126>76</x126>
      <y126>9</y126>
      <x127>74</x127>
      <y127>3</y127>
      <x128>72</x128>
      <y128>3</y128>
      <x129>66</x129>
      <y129>11</y129>
      <x130>63</x130>
      <y130>10</y130>
      <x131>63</x131>
      <y131>14</y131>
      <x132>68</x132>
      <y132>13</y132>
      <x133>70</x133>
      <y133>18</y133>
      <x134>68</x134>
      <y134>20</y134>
      <x135>59</x135>
      <y135>20</y135>
      <x136>58</x136>
      <y136>28</y136>
      <x137>49</x137>
      <y137>31</y137>
      <x138>51</x138>
      <y138>38</y138>
      <x139>47</x139>
      <y139>41</y139>
      <x140>50</x140>
      <y140>48</y140>
      <x141>46</x141>
      <y141>51</y141>
      <x142>40</x142>
      <y142>51</y142>
      <x143>41</x143>
      <y143>55</y143>
      <x144>45</x144>
      <y144>57</y144>
      <x145>39</x145>
      <y145>61</y145>
      <x146>40</x146>
      <y146>69</y146>
      <x147>37</x147>
      <y147>71</y147>
      <x148>35</x148>
      <y148>78</y148>
      <x149>29</x149>
      <y149>81</y149>
      <x150>29</x150>
      <y150>89</y150>
      <x151>21</x151>
      <y151>91</y151>
      <x152>22</x152>
      <y152>98</y152>
      <x153>19</x153>
      <y153>100</y153>
      <x154>19</x154>
      <y154>108</y154>
      <x155>11</x155>
      <y155>111</y155>
      <x156>8</x156>
      <y156>128</y156>
      <x157>0</x157>
      <y157>130</y157>
      <x158>0</x158>
      <y158>556</y158>
      <x159>4</x159>
      <y159>554</y159>
      <x160>4</x160>
      <y160>548</y160>
      <x161>8</x161>
      <y161>544</y161>
      <x162>11</x162>
      <y162>547</y162>
      <x163>8</x163>
      <y163>550</y163>
      <x164>7</x164>
      <y164>558</y164>
      <x165>0</x165>
      <y165>560</y165>
      <x166>2</x166>
      <y166>567</y166>
      <x167>0</x167>
      <y167>570</y167>
      <x168>0</x168>
      <y168>639</y168>
      <x169>139</x169>
      <y169>639</y169>
      <x170>141</x170>
      <y170>636</y170>
      <x171>144</x171>
      <y171>639</y171>
      <x172>304</x172>
      <y172>639</y172>
      <x173>317</x173>
      <y173>621</y173>
      <x174>316</x174>
      <y174>618</y174>
      <x175>323</x175>
      <y175>613</y175>
      <x176>323</x176>
      <y176>608</y176>
      <x177>334</x177>
      <y177>593</y177>
      <x178>333</x178>
      <y178>588</y178>
      <x179>341</x179>
      <y179>581</y179>
      <x180>340</x180>
      <y180>578</y180>
      <x181>346</x181>
      <y181>571</y181>
      <x182>344</x182>
      <y182>568</y182>
      <x183>351</x183>
      <y183>562</y183>
      <x184>349</x184>
      <y184>557</y184>
      <x185>353</x185>
      <y185>553</y185>
      <x186>353</x186>
      <y186>548</y186>
      <x187>364</x187>
      <y187>543</y187>
      <x188>365</x188>
      <y188>538</y188>
      <x189>377</x189>
      <y189>524</y189>
      <x190>378</x190>
      <y190>518</y190>
      <x191>384</x191>
      <y191>513</y191>
      <x192>385</x192>
      <y192>507</y192>
      <x193>389</x193>
      <y193>504</y193>
      <x194>400</x194>
      <y194>482</y194>
      <x195>409</x195>
      <y195>473</y195>
      <x196>409</x196>
      <y196>468</y196>
      <x197>424</x197>
      <y197>454</y197>
      <x198>424</x198>
      <y198>449</y198>
      <x199>427</x199>
      <y199>446</y199>
      <x200>425</x200>
      <y200>438</y200>
      <x201>428</x201>
      <y201>435</y201>
      <x202>437</x202>
      <y202>435</y202>
      <x203>435</x203>
      <y203>428</y203>
      <x204>441</x204>
      <y204>422</y204>
      <x205>443</x205>
      <y205>424</y205>
      <x206>444</x206>
      <y206>421</y206>
      <x207>440</x207>
      <y207>418</y207>
      <x208>448</x208>
      <y208>407</y208>
      <x209>453</x209>
      <y209>409</y209>
      <x210>452</x210>
      <y210>406</y210>
      <x211>464</x211>
      <y211>393</y211>
      <x212>459</x212>
      <y212>388</y212>
      <x213>472</x213>
      <y213>371</y213>
      <x214>472</x214>
      <y214>366</y214>
      <x215>476</x215>
      <y215>362</y215>
      <x216>475</x216>
      <y216>358</y216>
      <x217>478</x217>
      <y217>355</y217>
      <x218>481</x218>
      <y218>357</y218>
      <x219>484</x219>
      <y219>353</y219>
      <x220>484</x220>
      <y220>348</y220>
      <x221>489</x221>
      <y221>341</y221>
      <x222>486</x222>
      <y222>338</y222>
      <x223>490</x223>
      <y223>336</y223>
      <x224>488</x224>
      <y224>328</y224>
      <x225>494</x225>
      <y225>325</y225>
      <x226>495</x226>
      <y226>318</y226>
      <x227>513</x227>
      <y227>300</y227>
      <x228>517</x228>
      <y228>288</y228>
      <x229>525</x229>
      <y229>283</y229>
      <x230>525</x230>
      <y230>278</y230>
      <x231>538</x231>
      <y231>261</y231>
      <x232>537</x232>
      <y232>258</y232>
      <x233>543</x233>
      <y233>254</y233>
      <x234>545</x234>
      <y234>247</y234>
      <x235>555</x235>
      <y235>234</y235>
      <x236>555</x236>
      <y236>228</y236>
      <x237>562</x237>
      <y237>222</y237>
      <x238>567</x238>
      <y238>212</y238>
      <x239>565</x239>
      <y239>208</y239>
      <x240>585</x240>
      <y240>183</y240>
      <x241>585</x241>
      <y241>177</y241>
      <x242>587</x242>
      <y242>175</y242>
      <x243>591</x243>
      <y243>176</y243>
      <x244>597</x244>
      <y244>164</y244>
      <x245>604</x245>
      <y245>158</y245>
      <x246>605</x246>
      <y246>147</y246>
      <x247>612</x247>
      <y247>142</y247>
      <x248>609</x248>
      <y248>138</y248>
      <x249>615</x249>
      <y249>131</y249>
      <x250>614</x250>
      <y250>127</y250>
      <x251>623</x251>
      <y251>119</y251>
      <x252>627</x252>
      <y252>109</y252>
      <x253>624</x253>
      <y253>108</y253>
      <x254>630</x254>
      <y254>105</y254>
      <x255>636</x255>
      <y255>91</y255>
      <x256>633</x256>
      <y256>87</y256>
      <x257>636</x257>
      <y257>81</y257>
      <x258>624</x258>
      <y258>78</y258>
      <x259>628</x259>
      <y259>74</y259>
      <x260>631</x260>
      <y260>76</y260>
    </polygon>
  </object>
  <object>
    <name>aircraft</name>
    <bndbox>
      <xmin>215</xmin>
      <ymin>469</ymin>
      <xmax>265</xmax>
      <ymax>530</ymax>
    </bndbox>
    <polygon>
      <x1>243</x1>
      <y1>469</y1>
      <x2>246</x2>
      <y2>480</y2>
      <x3>253</x3>
      <y3>475</y3>
      <x4>255</x4>
      <y4>478</y4>
      <x5>250</x5>
      <y5>481</y5>
      <x6>252</x6>
      <y6>483</y6>
      <x7>250</x7>
      <y7>485</y7>
      <x8>245</x8>
      <y8>485</y8>
      <x9>245</x9>
      <y9>487</y9>
      <x10>255</x10>
      <y10>491</y10>
      <x11>256</x11>
      <y11>493</y11>
      <x12>251</x12>
      <y12>497</y12>
      <x13>253</x13>
      <y13>496</y13>
      <x14>256</x14>
      <y14>500</y14>
      <x15>261</x15>
      <y15>498</y15>
      <x16>265</x16>
      <y16>500</y16>
      <x17>264</x17>
      <y17>513</y17>
      <x18>258</x18>
      <y18>516</y18>
      <x19>234</x19>
      <y19>515</y19>
      <x20>236</x20>
      <y20>528</y20>
      <x21>230</x21>
      <y21>530</y21>
      <x22>232</x22>
      <y22>525</y22>
      <x23>228</x23>
      <y23>521</y23>
      <x24>232</x24>
      <y24>515</y24>
      <x25>225</x25>
      <y25>514</y25>
      <x26>226</x26>
      <y26>523</y26>
      <x27>221</x27>
      <y27>525</y27>
      <x28>219</x28>
      <y28>523</y28>
      <x29>221</x29>
      <y29>516</y29>
      <x30>215</x30>
      <y30>508</y30>
      <x31>223</x31>
      <y31>496</y31>
      <x32>226</x32>
      <y32>512</y32>
      <x33>229</x33>
      <y33>510</y33>
      <x34>230</x34>
      <y34>496</y34>
      <x35>227</x35>
      <y35>493</y35>
      <x36>229</x36>
      <y36>480</y36>
      <x37>236</x37>
      <y37>481</y37>
    </polygon>
  </object>
  <object>
    <name>aircraft</name>
    <bndbox>
      <xmin>278</xmin>
      <ymin>74</ymin>
      <xmax>547</xmax>
      <ymax>425</ymax>
    </bndbox>
    <polygon>
      <x1>483</x1>
      <y1>74</y1>
      <x2>485</x2>
      <y2>76</y2>
      <x3>483</x3>
      <y3>88</y3>
      <x4>474</x4>
      <y4>91</y4>
      <x5>477</x5>
      <y5>93</y5>
      <x6>475</x6>
      <y6>111</y6>
      <x7>479</x7>
      <y7>110</y7>
      <x8>482</x8>
      <y8>113</y8>
      <x9>481</x9>
      <y9>118</y9>
      <x10>488</x10>
      <y10>120</y10>
      <x11>490</x11>
      <y11>126</y11>
      <x12>495</x12>
      <y12>127</y12>
      <x13>490</x13>
      <y13>131</y13>
      <x14>495</x14>
      <y14>141</y14>
      <x15>493</x15>
      <y15>143</y15>
      <x16>494</x16>
      <y16>147</y16>
      <x17>513</x17>
      <y17>135</y17>
      <x18>518</x18>
      <y18>138</y18>
      <x19>521</x19>
      <y19>128</y19>
      <x20>539</x20>
      <y20>130</y20>
      <x21>541</x21>
      <y21>126</y21>
      <x22>543</x22>
      <y22>134</y22>
      <x23>547</x23>
      <y23>138</y23>
      <x24>535</x24>
      <y24>146</y24>
      <x25>541</x25>
      <y25>145</y25>
      <x26>542</x26>
      <y26>148</y26>
      <x27>530</x27>
      <y27>155</y27>
      <x28>530</x28>
      <y28>159</y28>
      <x29>525</x29>
      <y29>160</y29>
      <x30>523</x30>
      <y30>158</y30>
      <x31>518</x31>
      <y31>163</y31>
      <x32>519</x32>
      <y32>170</y32>
      <x33>511</x33>
      <y33>166</y33>
      <x34>510</x34>
      <y34>170</y34>
      <x35>500</x35>
      <y35>175</y35>
      <x36>501</x36>
      <y36>179</y36>
      <x37>505</x37>
      <y37>179</y37>
      <x38>503</x38>
      <y38>185</y38>
      <x39>498</x39>
      <y39>184</y39>
      <x40>498</x40>
      <y40>180</y40>
      <x41>494</x41>
      <y41>180</y41>
      <x42>493</x42>
      <y42>184</y42>
      <x43>490</x43>
      <y43>181</y43>
      <x44>480</x44>
      <y44>185</y44>
      <x45>477</x45>
      <y45>170</y45>
      <x46>461</x46>
      <y46>171</y46>
      <x47>460</x47>
      <y47>176</y47>
      <x48>466</x48>
      <y48>174</y48>
      <x49>468</x49>
      <y49>180</y49>
      <x50>473</x50>
      <y50>174</y50>
      <x51>478</x51>
      <y51>178</y51>
      <x52>470</x52>
      <y52>186</y52>
      <x53>472</x53>
      <y53>188</y53>
      <x54>468</x54>
      <y54>192</y54>
      <x55>464</x55>
      <y55>189</y55>
      <x56>464</x56>
      <y56>183</y56>
      <x57>461</x57>
      <y57>182</y57>
      <x58>460</x58>
      <y58>198</y58>
      <x59>452</x59>
      <y59>203</y59>
      <x60>455</x60>
      <y60>209</y60>
      <x61>450</x61>
      <y61>210</y61>
      <x62>449</x62>
      <y62>214</y62>
      <x63>446</x63>
      <y63>213</y63>
      <x64>447</x64>
      <y64>208</y64>
      <x65>450</x65>
      <y65>206</y65>
      <x66>447</x66>
      <y66>199</y66>
      <x67>443</x67>
      <y67>205</y67>
      <x68>437</x68>
      <y68>205</y68>
      <x69>437</x69>
      <y69>209</y69>
      <x70>426</x70>
      <y70>215</y70>
      <x71>426</x71>
      <y71>219</y71>
      <x72>433</x72>
      <y72>215</y72>
      <x73>435</x73>
      <y73>220</y73>
      <x74>433</x74>
      <y74>224</y74>
      <x75>425</x75>
      <y75>225</y75>
      <x76>425</x76>
      <y76>239</y76>
      <x77>419</x77>
      <y77>246</y77>
      <x78>423</x78>
      <y78>248</y78>
      <x79>423</x79>
      <y79>251</y79>
      <x80>415</x80>
      <y80>266</y80>
      <x81>421</x81>
      <y81>264</y81>
      <x82>424</x82>
      <y82>268</y82>
      <x83>422</x83>
      <y83>273</y83>
      <x84>420</x84>
      <y84>271</y84>
      <x85>415</x85>
      <y85>272</y85>
      <x86>411</x86>
      <y86>283</y86>
      <x87>409</x87>
      <y87>280</y87>
      <x88>399</x88>
      <y88>281</y88>
      <x89>403</x89>
      <y89>283</y89>
      <x90>400</x90>
      <y90>286</y90>
      <x91>401</x91>
      <y91>289</y91>
      <x92>389</x92>
      <y92>290</y92>
      <x93>391</x93>
      <y93>293</y93>
      <x94>389</x94>
      <y94>300</y94>
      <x95>379</x95>
      <y95>299</y95>
      <x96>375</x96>
      <y96>305</y96>
      <x97>365</x97>
      <y97>306</y97>
      <x98>373</x98>
      <y98>308</y98>
      <x99>366</x99>
      <y99>310</y99>
      <x100>365</x100>
      <y100>313</y100>
      <x101>366</x101>
      <y101>316</y101>
      <x102>371</x102>
      <y102>318</y102>
      <x103>369</x103>
      <y103>328</y103>
      <x104>366</x104>
      <y104>330</y104>
      <x105>364</x105>
      <y105>328</y105>
      <x106>366</x106>
      <y106>319</y106>
      <x107>361</x107>
      <y107>320</y107>
      <x108>358</x108>
      <y108>325</y108>
      <x109>355</x109>
      <y109>325</y109>
      <x110>355</x110>
      <y110>334</y110>
      <x111>345</x111>
      <y111>336</y111>
      <x112>347</x112>
      <y112>338</y112>
      <x113>353</x113>
      <y113>336</y113>
      <x114>355</x114>
      <y114>338</y114>
      <x115>352</x115>
      <y115>343</y115>
      <x116>335</x116>
      <y116>346</y116>
      <x117>336</x117>
      <y117>351</y117>
      <x118>342</x118>
      <y118>346</y118>
      <x119>343</x119>
      <y119>353</y119>
      <x120>343</x120>
      <y120>350</y120>
      <x121>347</x121>
      <y121>348</y121>
      <x122>349</x122>
      <y122>358</y122>
      <x123>339</x123>
      <y123>364</y123>
      <x124>339</x124>
      <y124>355</y124>
      <x125>335</x125>
      <y125>355</y125>
      <x126>336</x126>
      <y126>363</y126>
      <x127>333</x127>
      <y127>366</y127>
      <x128>325</x128>
      <y128>365</y128>
      <x129>326</x129>
      <y129>373</y129>
      <x130>322</x130>
      <y130>376</y130>
      <x131>322</x131>
      <y131>379</y131>
      <x132>326</x132>
      <y132>383</y132>
      <x133>319</x133>
      <y133>386</y133>
      <x134>325</x134>
      <y134>391</y134>
      <x135>323</x135>
      <y135>398</y135>
      <x136>325</x136>
      <y136>402</y136>
      <x137>320</x137>
      <y137>405</y137>
      <x138>319</x138>
      <y138>396</y138>
      <x139>316</x139>
      <y139>394</y139>
      <x140>313</x140>
      <y140>415</y140>
      <x141>296</x141>
      <y141>414</y141>
      <x142>295</x142>
      <y142>419</y142>
      <x143>290</x143>
      <y143>420</y143>
      <x144>290</x144>
      <y144>416</y144>
      <x145>286</x145>
      <y145>414</y145>
      <x146>284</x146>
      <y146>423</y146>
      <x147>281</x147>
      <y147>425</y147>
      <x148>278</x148>
      <y148>409</y148>
      <x149>281</x149>
      <y149>406</y149>
      <x150>279</x150>
      <y150>403</y150>
      <x151>283</x151>
      <y151>400</y151>
      <x152>286</x152>
      <y152>412</y152>
      <x153>289</x153>
      <y153>410</y153>
      <x154>289</x154>
      <y154>391</y154>
      <x155>291</x155>
      <y155>388</y155>
      <x156>296</x156>
      <y156>391</y156>
      <x157>299</x157>
      <y157>388</y157>
      <x158>297</x158>
      <y158>381</y158>
      <x159>301</x159>
      <y159>376</y159>
      <x160>301</x160>
      <y160>370</y160>
      <x161>305</x161>
      <y161>371</y161>
      <x162>305</x162>
      <y162>396</y162>
      <x163>307</x163>
      <y163>399</y163>
      <x164>309</x164>
      <y164>388</y164>
      <x165>317</x165>
      <y165>386</y165>
      <x166>306</x166>
      <y166>383</y166>
      <x167>311</x167>
      <y167>376</y167>
      <x168>315</x168>
      <y168>379</y168>
      <x169>317</x169>
      <y169>377</y169>
      <x170>316</x170>
      <y170>374</y170>
      <x171>311</x171>
      <y171>376</y171>
      <x172>308</x172>
      <y172>373</y172>
      <x173>310</x173>
      <y173>351</y173>
      <x174>314</x174>
      <y174>351</y174>
      <x175>316</x175>
      <y175>372</y175>
      <x176>324</x176>
      <y176>362</y176>
      <x177>317</x177>
      <y177>353</y177>
      <x178>320</x178>
      <y178>336</y178>
      <x179>322</x179>
      <y179>335</y179>
      <x180>326</x180>
      <y180>341</y180>
      <x181>331</x181>
      <y181>341</y181>
      <x182>331</x182>
      <y182>336</y182>
      <x183>336</x183>
      <y183>340</y183>
      <x184>339</x184>
      <y184>336</y184>
      <x185>331</x185>
      <y185>336</y185>
      <x186>328</x186>
      <y186>333</y186>
      <x187>328</x187>
      <y187>328</y187>
      <x188>331</x188>
      <y188>326</y188>
      <x189>330</x189>
      <y189>320</y189>
      <x190>335</x190>
      <y190>321</y190>
      <x191>336</x191>
      <y191>332</y191>
      <x192>340</x192>
      <y192>326</y192>
      <x193>338</x193>
      <y193>323</y193>
      <x194>340</x194>
      <y194>305</y194>
      <x195>344</x195>
      <y195>304</y195>
      <x196>346</x196>
      <y196>312</y196>
      <x197>349</x197>
      <y197>309</y197>
      <x198>349</x198>
      <y198>299</y198>
      <x199>351</x199>
      <y199>297</y199>
      <x200>356</x200>
      <y200>300</y200>
      <x201>359</x201>
      <y201>299</y201>
      <x202>359</x202>
      <y202>288</y202>
      <x203>361</x203>
      <y203>286</y203>
      <x204>358</x204>
      <y204>283</y204>
      <x205>359</x205>
      <y205>271</y205>
      <x206>361</x206>
      <y206>269</y206>
      <x207>365</x207>
      <y207>271</y207>
      <x208>366</x208>
      <y208>281</y208>
      <x209>369</x209>
      <y209>278</y209>
      <x210>367</x210>
      <y210>273</y210>
      <x211>370</x211>
      <y211>266</y211>
      <x212>369</x212>
      <y212>260</y212>
      <x213>373</x213>
      <y213>258</y213>
      <x214>376</x214>
      <y214>262</y214>
      <x215>380</x215>
      <y215>257</y215>
      <x216>378</x216>
      <y216>250</y216>
      <x217>381</x217>
      <y217>248</y217>
      <x218>389</x218>
      <y218>249</y218>
      <x219>389</x219>
      <y219>239</y219>
      <x220>399</x220>
      <y220>238</y220>
      <x221>398</x221>
      <y221>225</y221>
      <x222>394</x222>
      <y222>234</y222>
      <x223>389</x223>
      <y223>235</y223>
      <x224>389</x224>
      <y224>229</y224>
      <x225>397</x225>
      <y225>222</y225>
      <x226>399</x226>
      <y226>212</y226>
      <x227>405</x227>
      <y227>207</y227>
      <x228>407</x228>
      <y228>208</y228>
      <x229>405</x229>
      <y229>232</y229>
      <x230>411</x230>
      <y230>228</y230>
      <x231>416</x231>
      <y231>231</y231>
      <x232>419</x232>
      <y232>226</y232>
      <x233>418</x233>
      <y233>219</y233>
      <x234>413</x234>
      <y234>225</y234>
      <x235>409</x235>
      <y235>224</y235>
      <x236>408</x236>
      <y236>199</y236>
      <x237>410</x237>
      <y237>192</y237>
      <x238>418</x238>
      <y238>185</y238>
      <x239>420</x239>
      <y239>177</y239>
      <x240>425</x240>
      <y240>175</y240>
      <x241>427</x241>
      <y241>179</y241>
      <x242>429</x242>
      <y242>178</y242>
      <x243>428</x243>
      <y243>167</y243>
      <x244>430</x244>
      <y244>161</y244>
      <x245>439</x245>
      <y245>158</y245>
      <x246>437</x246>
      <y246>151</y246>
      <x247>442</x247>
      <y247>144</y247>
      <x248>448</x248>
      <y248>145</y248>
      <x249>448</x249>
      <y249>141</y249>
      <x250>452</x250>
      <y250>136</y250>
      <x251>460</x251>
      <y251>140</y251>
      <x252>460</x252>
      <y252>148</y252>
      <x253>468</x253>
      <y253>147</y253>
      <x254>463</x254>
      <y254>141</y254>
      <x255>466</x255>
      <y255>137</y255>
      <x256>469</x256>
      <y256>138</y256>
      <x257>468</x257>
      <y257>98</y257>
      <x258>466</x258>
      <y258>101</y258>
      <x259>463</x259>
      <y259>96</y259>
      <x260>466</x260>
      <y260>92</y260>
      <x261>468</x261>
      <y261>94</y261>
      <x262>467</x262>
      <y262>88</y262>
      <x263>470</x263>
      <y263>83</y263>
      <x264>473</x264>
      <y264>84</y264>
      <x265>473</x265>
      <y265>81</y265>
    </polygon>
  </object>
</annotation>
