<?xml version="1.0" ?>
<annotation>
  <folder>VOC</folder>
  <filename>4e9164aa-532e-4b76-bce4-060b090da357_0_1060_jpg.rf.9da6946dac072c28daa25bb73f5135c2.jpg</filename>
  <source>
    <database>roboflow.ai</database>
  </source>
  <size>
    <width>640</width>
    <height>640</height>
    <depth>3</depth>
  </size>
  <segmented>0</segmented>
  <object>
    <name>aircraft</name>
    <bndbox>
      <xmin>217</xmin>
      <ymin>246</ymin>
      <xmax>273</xmax>
      <ymax>301</ymax>
    </bndbox>
    <polygon>
      <x1>256</x1>
      <y1>246</y1>
      <x2>254</x2>
      <y2>246</y2>
      <x3>250</x3>
      <y3>269</y3>
      <x4>247</x4>
      <y4>273</y4>
      <x5>234</x5>
      <y5>266</y5>
      <x6>230</x6>
      <y6>254</y6>
      <x7>227</x7>
      <y7>263</y7>
      <x8>217</x8>
      <y8>273</y8>
      <x9>218</x9>
      <y9>275</y9>
      <x10>233</x10>
      <y10>273</y10>
      <x11>242</x11>
      <y11>280</y11>
      <x12>222</x12>
      <y12>297</y12>
      <x13>223</x13>
      <y13>301</y13>
      <x14>236</x14>
      <y14>297</y14>
      <x15>241</x15>
      <y15>298</y15>
      <x16>243</x16>
      <y16>294</y16>
      <x17>251</x17>
      <y17>293</y17>
      <x18>254</x18>
      <y18>289</y18>
      <x19>269</x19>
      <y19>294</y19>
      <x20>273</x20>
      <y20>293</y20>
      <x21>261</x21>
      <y21>283</y21>
      <x22>263</x22>
      <y22>272</y22>
      <x23>260</x23>
      <y23>266</y23>
      <x24>262</x24>
      <y24>262</y24>
      <x25>258</x25>
      <y25>258</y25>
    </polygon>
  </object>
  <object>
    <name>aircraft</name>
    <bndbox>
      <xmin>65</xmin>
      <ymin>454</ymin>
      <xmax>120</xmax>
      <ymax>509</ymax>
    </bndbox>
    <polygon>
      <x1>112</x1>
      <y1>454</y1>
      <x2>110</x2>
      <y2>454</y2>
      <x3>101</x3>
      <y3>466</y3>
      <x4>71</x4>
      <y4>467</y4>
      <x5>65</x5>
      <y5>469</y5>
      <x6>66</x6>
      <y6>472</y6>
      <x7>90</x7>
      <y7>476</y7>
      <x8>92</x8>
      <y8>478</y8>
      <x9>86</x9>
      <y9>490</y9>
      <x10>83</x10>
      <y10>493</y10>
      <x11>74</x11>
      <y11>494</y11>
      <x12>73</x12>
      <y12>497</y12>
      <x13>76</x13>
      <y13>499</y13>
      <x14>84</x14>
      <y14>500</y14>
      <x15>93</x15>
      <y15>509</y15>
      <x16>93</x16>
      <y16>503</y16>
      <x17>91</x17>
      <y17>496</y17>
      <x18>100</x18>
      <y18>484</y18>
      <x19>108</x19>
      <y19>491</y19>
      <x20>118</x20>
      <y20>504</y20>
      <x21>120</x21>
      <y21>503</y21>
      <x22>115</x22>
      <y22>487</y22>
      <x23>108</x23>
      <y23>472</y23>
      <x24>112</x24>
      <y24>464</y24>
      <x25>113</x25>
      <y25>456</y25>
    </polygon>
  </object>
  <object>
    <name>aircraft</name>
    <bndbox>
      <xmin>182</xmin>
      <ymin>88</ymin>
      <xmax>266</xmax>
      <ymax>131</ymax>
    </bndbox>
    <polygon>
      <x1>182</x1>
      <y1>90</y1>
      <x2>183</x2>
      <y2>95</y2>
      <x3>193</x3>
      <y3>99</y3>
      <x4>195</x4>
      <y4>101</y4>
      <x5>203</x5>
      <y5>105</y5>
      <x6>218</x6>
      <y6>115</y6>
      <x7>234</x7>
      <y7>123</y7>
      <x8>236</x8>
      <y8>123</y8>
      <x9>239</x9>
      <y9>125</y9>
      <x10>242</x10>
      <y10>125</y10>
      <x11>252</x11>
      <y11>129</y11>
      <x12>255</x12>
      <y12>129</y12>
      <x13>259</x13>
      <y13>131</y13>
      <x14>262</x14>
      <y14>131</y14>
      <x15>265</x15>
      <y15>127</y15>
      <x16>266</x16>
      <y16>123</y16>
      <x17>262</x17>
      <y17>119</y17>
      <x18>257</x18>
      <y18>117</y18>
      <x19>250</x19>
      <y19>112</y19>
      <x20>238</x20>
      <y20>107</y20>
      <x21>236</x21>
      <y21>105</y21>
      <x22>228</x22>
      <y22>101</y22>
      <x23>225</x23>
      <y23>98</y23>
      <x24>215</x24>
      <y24>93</y24>
      <x25>211</x25>
      <y25>89</y25>
      <x26>184</x26>
      <y26>88</y26>
    </polygon>
  </object>
  <object>
    <name>aircraft</name>
    <bndbox>
      <xmin>507</xmin>
      <ymin>0</ymin>
      <xmax>560</xmax>
      <ymax>27</ymax>
    </bndbox>
    <polygon>
      <x1>507</x1>
      <y1>0</y1>
      <x2>507</x2>
      <y2>2</y2>
      <x3>516</x3>
      <y3>1</y3>
      <x4>529</x4>
      <y4>10</y4>
      <x5>529</x5>
      <y5>12</y5>
      <x6>515</x6>
      <y6>24</y6>
      <x7>516</x7>
      <y7>27</y7>
      <x8>532</x8>
      <y8>20</y8>
      <x9>538</x9>
      <y9>21</y9>
      <x10>541</x10>
      <y10>18</y10>
      <x11>557</x11>
      <y11>25</y11>
      <x12>560</x12>
      <y12>24</y12>
      <x13>557</x13>
      <y13>19</y13>
      <x14>545</x14>
      <y14>11</y14>
      <x15>547</x15>
      <y15>4</y15>
      <x16>543</x16>
      <y16>0</y16>
      <x17>536</x17>
      <y17>0</y17>
      <x18>533</x18>
      <y18>3</y18>
      <x19>527</x19>
      <y19>0</y19>
    </polygon>
  </object>
  <object>
    <name>aircraft</name>
    <bndbox>
      <xmin>448</xmin>
      <ymin>581</ymin>
      <xmax>501</xmax>
      <ymax>635</ymax>
    </bndbox>
    <polygon>
      <x1>496</x1>
      <y1>581</y1>
      <x2>479</x2>
      <y2>584</y2>
      <x3>474</x3>
      <y3>588</y3>
      <x4>469</x4>
      <y4>588</y4>
      <x5>463</x5>
      <y5>593</y5>
      <x6>448</x6>
      <y6>588</y6>
      <x7>449</x7>
      <y7>593</y7>
      <x8>458</x8>
      <y8>602</y8>
      <x9>461</x9>
      <y9>631</y9>
      <x10>464</x10>
      <y10>635</y10>
      <x11>467</x11>
      <y11>634</y11>
      <x12>468</x12>
      <y12>620</y12>
      <x13>470</x13>
      <y13>613</y13>
      <x14>473</x14>
      <y14>610</y14>
      <x15>485</x15>
      <y15>616</y15>
      <x16>488</x16>
      <y16>628</y16>
      <x17>491</x17>
      <y17>626</y17>
      <x18>501</x18>
      <y18>610</y18>
      <x19>501</x19>
      <y19>608</y19>
      <x20>498</x20>
      <y20>607</y20>
      <x21>489</x21>
      <y21>611</y21>
      <x22>477</x22>
      <y22>601</y22>
      <x23>497</x23>
      <y23>584</y23>
    </polygon>
  </object>
  <object>
    <name>aircraft</name>
    <bndbox>
      <xmin>351</xmin>
      <ymin>419</ymin>
      <xmax>405</xmax>
      <ymax>474</ymax>
    </bndbox>
    <polygon>
      <x1>376</x1>
      <y1>419</y1>
      <x2>376</x2>
      <y2>425</y2>
      <x3>379</x3>
      <y3>431</y3>
      <x4>371</x4>
      <y4>444</y4>
      <x5>368</x5>
      <y5>444</y5>
      <x6>353</x6>
      <y6>424</y6>
      <x7>351</x7>
      <y7>424</y7>
      <x8>354</x8>
      <y8>443</y8>
      <x9>358</x9>
      <y9>453</y9>
      <x10>362</x10>
      <y10>456</y10>
      <x11>362</x11>
      <y11>461</y11>
      <x12>357</x12>
      <y12>471</y12>
      <x13>358</x13>
      <y13>474</y13>
      <x14>362</x14>
      <y14>474</y14>
      <x15>372</x15>
      <y15>464</y15>
      <x16>389</x16>
      <y16>463</y16>
      <x17>405</x17>
      <y17>459</y17>
      <x18>402</x18>
      <y18>455</y18>
      <x19>381</x19>
      <y19>452</y19>
      <x20>379</x20>
      <y20>450</y20>
      <x21>386</x21>
      <y21>437</y21>
      <x22>395</x22>
      <y22>436</y22>
      <x23>397</x23>
      <y23>433</y23>
      <x24>386</x24>
      <y24>428</y24>
    </polygon>
  </object>
  <object>
    <name>aircraft</name>
    <bndbox>
      <xmin>526</xmin>
      <ymin>285</ymin>
      <xmax>587</xmax>
      <ymax>335</ymax>
    </bndbox>
    <polygon>
      <x1>527</x1>
      <y1>286</y1>
      <x2>526</x2>
      <y2>288</y2>
      <x3>527</x3>
      <y3>289</y3>
      <x4>527</x4>
      <y4>291</y4>
      <x5>530</x5>
      <y5>295</y5>
      <x6>532</x6>
      <y6>300</y6>
      <x7>544</x7>
      <y7>314</y7>
      <x8>549</x8>
      <y8>317</y8>
      <x9>551</x9>
      <y9>317</y9>
      <x10>576</x10>
      <y10>335</y10>
      <x11>580</x11>
      <y11>335</y11>
      <x12>583</x12>
      <y12>332</y12>
      <x13>587</x13>
      <y13>326</y13>
      <x14>587</x14>
      <y14>323</y14>
      <x15>577</x15>
      <y15>317</y15>
      <x16>574</x16>
      <y16>314</y16>
      <x17>533</x17>
      <y17>287</y17>
      <x18>529</x18>
      <y18>285</y18>
    </polygon>
  </object>
  <object>
    <name>aircraft</name>
    <bndbox>
      <xmin>424</xmin>
      <ymin>502</ymin>
      <xmax>461</xmax>
      <ymax>543</ymax>
    </bndbox>
    <polygon>
      <x1>431</x1>
      <y1>502</y1>
      <x2>424</x2>
      <y2>515</y2>
      <x3>436</x3>
      <y3>526</y3>
      <x4>432</x4>
      <y4>539</y4>
      <x5>437</x5>
      <y5>543</y5>
      <x6>446</x6>
      <y6>534</y6>
      <x7>449</x7>
      <y7>534</y7>
      <x8>453</x8>
      <y8>527</y8>
      <x9>461</x9>
      <y9>521</y9>
      <x10>459</x10>
      <y10>520</y10>
      <x11>455</x11>
      <y11>523</y11>
      <x12>449</x12>
      <y12>515</y12>
      <x13>443</x13>
      <y13>513</y13>
      <x14>434</x14>
      <y14>502</y14>
    </polygon>
  </object>
</annotation>
